[
{"name":"Orléans","latitude":"47.9025","longitude":"1.9043","population":"113224","region":"24","departement":"45","arrondissement":"452","commune":"45234"},
{"name":"Fleury-les-Aubrais","latitude":"47.93194","longitude":"1.92111","population":"21118","region":"24","departement":"45","arrondissement":"452","commune":"45147"},
{"name":"Olivet","latitude":"47.86306","longitude":"1.89972","population":"19806","region":"24","departement":"45","arrondissement":"452","commune":"45232"},
{"name":"Saint-Jean-de-Braye","latitude":"47.9124","longitude":"1.9718","population":"19102","region":"24","departement":"45","arrondissement":"452","commune":"45284"},
{"name":"Saint-Jean-de-la-Ruelle","latitude":"47.91306","longitude":"1.87333","population":"16628","region":"24","departement":"45","arrondissement":"452","commune":"45285"},
{"name":"Saran","latitude":"47.95139","longitude":"1.88028","population":"15240","region":"24","departement":"45","arrondissement":"452","commune":"45302"},
{"name":"La Chapelle-Saint-Mesmin","latitude":"47.88972","longitude":"1.83972","population":"9515","region":"24","departement":"45","arrondissement":"452","commune":"45075"},
{"name":"Saint-Jean-le-Blanc","latitude":"47.89194","longitude":"1.91722","population":"8234","region":"24","departement":"45","arrondissement":"452","commune":"45286"},
{"name":"Chécy","latitude":"47.89361","longitude":"2.02694","population":"8201","region":"24","departement":"45","arrondissement":"452","commune":"45089"},
{"name":"Ingré","latitude":"47.92056","longitude":"1.82417","population":"7885","region":"24","departement":"45","arrondissement":"452","commune":"45169"},
{"name":"Saint-Denis-en-Val","latitude":"47.87722","longitude":"1.96","population":"7169","region":"24","departement":"45","arrondissement":"452","commune":"45274"},
{"name":"Saint-Pryvé-Saint-Mesmin","latitude":"47.88083","longitude":"1.86778","population":"5224","region":"24","departement":"45","arrondissement":"452","commune":"45298"},
{"name":"Sandillon","latitude":"47.84528","longitude":"2.0325","population":"3802","region":"24","departement":"45","arrondissement":"452","commune":"45300"},
{"name":"Chaingy","latitude":"47.88361","longitude":"1.77306","population":"3482","region":"24","departement":"45","arrondissement":"452","commune":"45067"},
{"name":"Ormes","latitude":"47.94111","longitude":"1.82056","population":"3411","region":"24","departement":"45","arrondissement":"452","commune":"45235"},
{"name":"Saint-Cyr-en-Val","latitude":"47.83","longitude":"1.96944","population":"3170","region":"24","departement":"45","arrondissement":"452","commune":"45272"},
{"name":"Traînou","latitude":"47.97306","longitude":"2.105","population":"3076","region":"24","departement":"45","arrondissement":"452","commune":"45327"},
{"name":"Semoy","latitude":"47.93222","longitude":"1.94861","population":"3009","region":"24","departement":"45","arrondissement":"452","commune":"45308"},
{"name":"Saint-Hilaire-Saint-Mesmin","latitude":"47.86556","longitude":"1.835","population":"2804","region":"24","departement":"45","arrondissement":"452","commune":"45282"},
{"name":"Mardié","latitude":"47.88694","longitude":"2.05667","population":"2576","region":"24","departement":"45","arrondissement":"452","commune":"45194"},
{"name":"Donnery","latitude":"47.91306","longitude":"2.10417","population":"2462","region":"24","departement":"45","arrondissement":"452","commune":"45126"},
{"name":"Boigny-sur-Bionne","latitude":"47.9275","longitude":"2.00944","population":"2139","region":"24","departement":"45","arrondissement":"452","commune":"45034"},
{"name":"Marcilly-en-Villette","latitude":"47.76417","longitude":"2.02194","population":"1980","region":"24","departement":"45","arrondissement":"452","commune":"45193"},
{"name":"Darvoy","latitude":"47.85722","longitude":"2.09917","population":"1862","region":"24","departement":"45","arrondissement":"452","commune":"45123"},
{"name":"Gidy","latitude":"47.98694","longitude":"1.83667","population":"1543","region":"24","departement":"45","arrondissement":"452","commune":"45154"},
{"name":"Vennecy","latitude":"47.95389","longitude":"2.05528","population":"1394","region":"24","departement":"45","arrondissement":"452","commune":"45333"},
{"name":"Rebréchien","latitude":"47.98778","longitude":"2.04472","population":"1361","region":"24","departement":"45","arrondissement":"452","commune":"45261"},
{"name":"Mareau-aux-Prés","latitude":"47.8476","longitude":"1.7999","population":"1275","region":"24","departement":"45","arrondissement":"452","commune":"45196"},
{"name":"Chanteau","latitude":"47.96472","longitude":"1.96833","population":"1230","region":"24","departement":"45","arrondissement":"452","commune":"45072"},
{"name":"Cercottes","latitude":"47.98528","longitude":"1.88278","population":"1184","region":"24","departement":"45","arrondissement":"452","commune":"45062"},
{"name":"Férolles","latitude":"47.835","longitude":"2.10861","population":"1155","region":"24","departement":"45","arrondissement":"452","commune":"45144"},
{"name":"Ardon","latitude":"47.77833","longitude":"1.87389","population":"1125","region":"24","departement":"45","arrondissement":"452","commune":"45006"},
{"name":"Marigny-les-Usages","latitude":"47.95722","longitude":"2.01639","population":"1125","region":"24","departement":"45","arrondissement":"452","commune":"45197"},
{"name":"Boulay-les-Barres","latitude":"47.98028","longitude":"1.78361","population":"1119","region":"24","departement":"45","arrondissement":"452","commune":"45046"},
{"name":"Bou","latitude":"47.87333","longitude":"2.0475","population":"895","region":"24","departement":"45","arrondissement":"452","commune":"45043"},
{"name":"Mézières-lez-Cléry","latitude":"47.81861","longitude":"1.80417","population":"778","region":"24","departement":"45","arrondissement":"452","commune":"45204"},
{"name":"Combleux","latitude":"47.89972","longitude":"1.99056","population":"467","region":"24","departement":"45","arrondissement":"452","commune":"45100"},
{"name":"Bucy-Saint-Liphard","latitude":"47.93583","longitude":"1.765","population":"206","region":"24","departement":"45","arrondissement":"452","commune":"45059"}
]