[
{"name":"Marmande","latitude":"44.5","longitude":"0.16528","population":"18476","region":"75","departement":"47","arrondissement":"472","commune":"47157"},
{"name":"Tonneins","latitude":"44.38972","longitude":"0.30833","population":"9063","region":"75","departement":"47","arrondissement":"472","commune":"47310"},
{"name":"Sainte-Bazeille","latitude":"44.53028","longitude":"0.09417","population":"2986","region":"75","departement":"47","arrondissement":"472","commune":"47233"},
{"name":"Virazeil","latitude":"44.50722","longitude":"0.21861","population":"1666","region":"75","departement":"47","arrondissement":"472","commune":"47326"},
{"name":"Gontaud-de-Nogaret","latitude":"44.4564","longitude":"0.296","population":"1617","region":"75","departement":"47","arrondissement":"472","commune":"47110"},
{"name":"Le Mas-d'Agenais","latitude":"44.4105","longitude":"0.2177","population":"1431","region":"75","departement":"47","arrondissement":"472","commune":"47159"},
{"name":"Beaupuy","latitude":"44.53556","longitude":"0.14583","population":"1426","region":"75","departement":"47","arrondissement":"472","commune":"47024"},
{"name":"Meilhan-sur-Garonne","latitude":"44.52139","longitude":"0.03361","population":"1320","region":"75","departement":"47","arrondissement":"472","commune":"47165"},
{"name":"Fourques-sur-Garonne","latitude":"44.44861","longitude":"0.15833","population":"1221","region":"75","departement":"47","arrondissement":"472","commune":"47101"},
{"name":"Lamothe-Landerron","latitude":"44.55833","longitude":"0.06083","population":"1108","region":"75","departement":"33","arrondissement":"333","commune":"33221"},
{"name":"Seyches","latitude":"44.54972","longitude":"0.305","population":"1011","region":"75","departement":"47","arrondissement":"472","commune":"47301"},
{"name":"Cocumont","latitude":"44.44861","longitude":"0.02611","population":"973","region":"75","departement":"47","arrondissement":"472","commune":"47068"},
{"name":"Samazan","latitude":"44.43389","longitude":"0.11222","population":"859","region":"75","departement":"47","arrondissement":"472","commune":"47285"},
{"name":"Fauillet","latitude":"44.42583","longitude":"0.29","population":"855","region":"75","departement":"47","arrondissement":"472","commune":"47095"},
{"name":"Castelnau-sur-Gupie","latitude":"44.55972","longitude":"0.1325","population":"828","region":"75","departement":"47","arrondissement":"472","commune":"47056"},
{"name":"Marcellus","latitude":"44.48083","longitude":"0.07806","population":"800","region":"75","departement":"47","arrondissement":"472","commune":"47156"},
{"name":"Birac-sur-Trec","latitude":"44.4861","longitude":"0.2654","population":"796","region":"75","departement":"47","arrondissement":"472","commune":"47028"},
{"name":"Montpouillan","latitude":"44.4681","longitude":"0.1061","population":"655","region":"75","departement":"47","arrondissement":"472","commune":"47191"},
{"name":"Fauguerolles","latitude":"44.44056","longitude":"0.24917","population":"637","region":"75","departement":"47","arrondissement":"472","commune":"47094"},
{"name":"Caumont-sur-Garonne","latitude":"44.4384","longitude":"0.1817","population":"620","region":"75","departement":"47","arrondissement":"472","commune":"47061"},
{"name":"Lagupie","latitude":"44.55639","longitude":"0.11472","population":"610","region":"75","departement":"47","arrondissement":"472","commune":"47131"},
{"name":"Bouglon","latitude":"44.3934","longitude":"0.098","population":"604","region":"75","departement":"47","arrondissement":"472","commune":"47034"},
{"name":"Saint-Pardoux-du-Breuil","latitude":"44.47639","longitude":"0.19306","population":"590","region":"75","departement":"47","arrondissement":"472","commune":"47263"},
{"name":"Calonges","latitude":"44.37389","longitude":"0.24083","population":"581","region":"75","departement":"47","arrondissement":"472","commune":"47046"},
{"name":"Mongauzy","latitude":"44.56667","longitude":"0.03333","population":"570","region":"75","departement":"33","arrondissement":"333","commune":"33287"},
{"name":"Puymiclan","latitude":"44.51222","longitude":"0.31583","population":"565","region":"75","departement":"47","arrondissement":"472","commune":"47216"},
{"name":"Escassefort","latitude":"44.54833","longitude":"0.2375","population":"563","region":"75","departement":"47","arrondissement":"472","commune":"47088"},
{"name":"Villeton","latitude":"44.3619","longitude":"0.2726","population":"524","region":"75","departement":"47","arrondissement":"472","commune":"47325"},
{"name":"Hure","latitude":"44.54472","longitude":"0.00056","population":"491","region":"75","departement":"33","arrondissement":"333","commune":"33204"},
{"name":"Sainte-Marthe","latitude":"44.4141","longitude":"0.1493","population":"481","region":"75","departement":"47","arrondissement":"472","commune":"47253"},
{"name":"Mauvezin-sur-Gupie","latitude":"44.55583","longitude":"0.16556","population":"477","region":"75","departement":"47","arrondissement":"472","commune":"47163"},
{"name":"Saint-Martin-Petit","latitude":"44.5617","longitude":"0.0854","population":"430","region":"75","departement":"47","arrondissement":"472","commune":"47257"},
{"name":"Couthures-sur-Garonne","latitude":"44.51361","longitude":"0.07806","population":"397","region":"75","departement":"47","arrondissement":"472","commune":"47074"},
{"name":"Grézet-Cavagnan","latitude":"44.38361","longitude":"0.13194","population":"353","region":"75","departement":"47","arrondissement":"472","commune":"47114"},
{"name":"Sainte-Gemme-Martaillac","latitude":"44.36639","longitude":"0.15222","population":"340","region":"75","departement":"47","arrondissement":"472","commune":"47244"},
{"name":"Longueville","latitude":"44.46167","longitude":"0.21611","population":"337","region":"75","departement":"47","arrondissement":"472","commune":"47150"},
{"name":"Argenton","latitude":"44.385","longitude":"0.09389","population":"324","region":"75","departement":"47","arrondissement":"472","commune":"47013"},
{"name":"Lagruère","latitude":"44.4015","longitude":"0.2429","population":"324","region":"75","departement":"47","arrondissement":"472","commune":"47130"},
{"name":"Poussignac","latitude":"44.35694","longitude":"0.07056","population":"292","region":"75","departement":"47","arrondissement":"472","commune":"47212"},
{"name":"Gaujac","latitude":"44.4897","longitude":"0.1115","population":"286","region":"75","departement":"47","arrondissement":"472","commune":"47108"},
{"name":"Peyrière","latitude":"44.57556","longitude":"0.31778","population":"278","region":"75","departement":"47","arrondissement":"472","commune":"47204"},
{"name":"Guérin","latitude":"44.41","longitude":"0.06889","population":"241","region":"75","departement":"47","arrondissement":"472","commune":"47115"},
{"name":"Razimet","latitude":"44.35222","longitude":"0.23472","population":"225","region":"75","departement":"47","arrondissement":"474","commune":"47220"},
{"name":"Monheurt","latitude":"44.34028","longitude":"0.3075","population":"215","region":"75","departement":"47","arrondissement":"474","commune":"47177"},
{"name":"Antagnac","latitude":"44.35278","longitude":"0.00861","population":"213","region":"75","departement":"47","arrondissement":"472","commune":"47010"},
{"name":"Sénestis","latitude":"44.42194","longitude":"0.23083","population":"197","region":"75","departement":"47","arrondissement":"472","commune":"47298"},
{"name":"Saint-Michel-de-Lapujade","latitude":"44.5815","longitude":"0.071","population":"196","region":"75","departement":"33","arrondissement":"333","commune":"33453"},
{"name":"Ruffiac","latitude":"44.36194","longitude":"0.03333","population":"176","region":"75","departement":"47","arrondissement":"472","commune":"47227"},
{"name":"Montagoudin","latitude":"44.5779","longitude":"0.0008","population":"165","region":"75","departement":"33","arrondissement":"333","commune":"33291"},
{"name":"Saint-Avit","latitude":"44.568","longitude":"0.2132","population":"163","region":"75","departement":"47","arrondissement":"472","commune":"47231"},
{"name":"Romestaing","latitude":"44.41694","longitude":"0.00306","population":"151","region":"75","departement":"47","arrondissement":"472","commune":"47224"},
{"name":"Montignac-Toupinerie","latitude":"44.54833","longitude":"0.34528","population":"135","region":"75","departement":"47","arrondissement":"472","commune":"47189"},
{"name":"Agmé","latitude":"44.49028","longitude":"0.34611","population":"131","region":"75","departement":"47","arrondissement":"472","commune":"47002"},
{"name":"Bourdelles","latitude":"44.55333","longitude":"0.00028","population":"120","region":"75","departement":"33","arrondissement":"333","commune":"33066"},
{"name":"Jusix","latitude":"44.54028","longitude":"0.04944","population":"111","region":"75","departement":"47","arrondissement":"472","commune":"47120"},
{"name":"Lachapelle","latitude":"44.57556","longitude":"0.26278","population":"87","region":"75","departement":"47","arrondissement":"472","commune":"47126"},
{"name":"Taillebourg","latitude":"44.44694","longitude":"0.20861","population":"87","region":"75","departement":"47","arrondissement":"472","commune":"47304"}
]