[
{"name":"Gérardmer","latitude":"48.07222","longitude":"6.87861","population":"8757","region":"44","departement":"88","arrondissement":"883","commune":"88196"},
{"name":"La Bresse","latitude":"48.00583","longitude":"6.87583","population":"4732","region":"44","departement":"88","arrondissement":"881","commune":"88075"},
{"name":"Vagney","latitude":"48.00833","longitude":"6.71639","population":"4014","region":"44","departement":"88","arrondissement":"881","commune":"88486"},
{"name":"Anould","latitude":"48.18556","longitude":"6.94556","population":"3336","region":"44","departement":"88","arrondissement":"883","commune":"88009"},
{"name":"Bruyères","latitude":"48.20833","longitude":"6.71861","population":"3291","region":"44","departement":"88","arrondissement":"881","commune":"88078"},
{"name":"Fraize","latitude":"48.18583","longitude":"7.00139","population":"3056","region":"44","departement":"88","arrondissement":"883","commune":"88181"},
{"name":"Granges-Aumontzey","latitude":"48.14556","longitude":"6.78861","population":"2302","region":"44","departement":"88","arrondissement":"883","commune":"88218"},
{"name":"Le Syndicat","latitude":"48.02361","longitude":"6.68472","population":"1911","region":"44","departement":"88","arrondissement":"881","commune":"88462"},
{"name":"Plainfaing","latitude":"48.17222","longitude":"7.01361","population":"1827","region":"44","departement":"88","arrondissement":"883","commune":"88349"},
{"name":"Corcieux","latitude":"48.17222","longitude":"6.87944","population":"1668","region":"44","departement":"88","arrondissement":"883","commune":"88115"},
{"name":"Le Tholy","latitude":"48.08306","longitude":"6.74389","population":"1589","region":"44","departement":"88","arrondissement":"881","commune":"88470"},
{"name":"Xonrupt-Longemer","latitude":"48.08056","longitude":"6.92583","population":"1580","region":"44","departement":"88","arrondissement":"883","commune":"88531"},
{"name":"Saint-Léonard","latitude":"48.21639","longitude":"6.94389","population":"1394","region":"44","departement":"88","arrondissement":"883","commune":"88423"},
{"name":"Ban-sur-Meurthe-Clefcy","latitude":"48.1725","longitude":"6.97917","population":"958","region":"44","departement":"88","arrondissement":"883","commune":"88106"},
{"name":"Rochesson","latitude":"48.02222","longitude":"6.78611","population":"687","region":"44","departement":"88","arrondissement":"881","commune":"88391"},
{"name":"Laveline-devant-Bruyères","latitude":"48.18389","longitude":"6.75972","population":"650","region":"44","departement":"88","arrondissement":"881","commune":"88262"},
{"name":"Sapois","latitude":"48.01694","longitude":"6.74639","population":"649","region":"44","departement":"88","arrondissement":"881","commune":"88442"},
{"name":"Mandray","latitude":"48.21833","longitude":"6.99583","population":"627","region":"44","departement":"88","arrondissement":"883","commune":"88284"},
{"name":"Laval-sur-Vologne","latitude":"48.19472","longitude":"6.70028","population":"623","region":"44","departement":"88","arrondissement":"881","commune":"88261"},
{"name":"La Chapelle-devant-Bruyères","latitude":"48.1851","longitude":"6.7886","population":"621","region":"44","departement":"88","arrondissement":"883","commune":"88089"},
{"name":"La Houssière","latitude":"48.19528","longitude":"6.85389","population":"575","region":"44","departement":"88","arrondissement":"883","commune":"88244"},
{"name":"La Forge","latitude":"48.06556","longitude":"6.72444","population":"570","region":"44","departement":"88","arrondissement":"881","commune":"88177"},
{"name":"Gerbépal","latitude":"48.15","longitude":"6.92194","population":"544","region":"44","departement":"88","arrondissement":"883","commune":"88198"},
{"name":"Champ-le-Duc","latitude":"48.19417","longitude":"6.71944","population":"542","region":"44","departement":"88","arrondissement":"881","commune":"88086"},
{"name":"Biffontaine","latitude":"48.21111","longitude":"6.80472","population":"444","region":"44","departement":"88","arrondissement":"883","commune":"88059"},
{"name":"Gerbamont","latitude":"48.0051","longitude":"6.7553","population":"372","region":"44","departement":"88","arrondissement":"881","commune":"88197"},
{"name":"Mittlach","latitude":"48.0042","longitude":"7.0307","population":"323","region":"44","departement":"68","arrondissement":"682","commune":"68210"},
{"name":"Jussarupt","latitude":"48.15972","longitude":"6.75306","population":"295","region":"44","departement":"88","arrondissement":"883","commune":"88256"},
{"name":"Liézey","latitude":"48.09361","longitude":"6.80528","population":"284","region":"44","departement":"88","arrondissement":"883","commune":"88269"},
{"name":"Fiménil","latitude":"48.18417","longitude":"6.71417","population":"262","region":"44","departement":"88","arrondissement":"881","commune":"88172"},
{"name":"Herpelmont","latitude":"48.16944","longitude":"6.73944","population":"247","region":"44","departement":"88","arrondissement":"883","commune":"88240"},
{"name":"Les Poulières","latitude":"48.19778","longitude":"6.79111","population":"239","region":"44","departement":"88","arrondissement":"883","commune":"88356"},
{"name":"Laveline-du-Houx","latitude":"48.13722","longitude":"6.7","population":"221","region":"44","departement":"88","arrondissement":"881","commune":"88263"},
{"name":"Rehaupal","latitude":"48.11944","longitude":"6.73194","population":"193","region":"44","departement":"88","arrondissement":"883","commune":"88380"},
{"name":"Arrentès-de-Corcieux","latitude":"48.1446","longitude":"6.8651","population":"167","region":"44","departement":"88","arrondissement":"883","commune":"88014"},
{"name":"Champdray","latitude":"48.13528","longitude":"6.75278","population":"160","region":"44","departement":"88","arrondissement":"883","commune":"88085"},
{"name":"Vervezelle","latitude":"48.22167","longitude":"6.73917","population":"148","region":"44","departement":"88","arrondissement":"883","commune":"88502"},
{"name":"Barbey-Seroux","latitude":"48.14167","longitude":"6.83944","population":"140","region":"44","departement":"88","arrondissement":"883","commune":"88035"},
{"name":"Beauménil","latitude":"48.18028","longitude":"6.72806","population":"126","region":"44","departement":"88","arrondissement":"881","commune":"88046"},
{"name":"Vienville","latitude":"48.17444","longitude":"6.83028","population":"125","region":"44","departement":"88","arrondissement":"883","commune":"88505"},
{"name":"Prey","latitude":"48.17889","longitude":"6.68556","population":"91","region":"44","departement":"88","arrondissement":"881","commune":"88359"},
{"name":"Le Valtin","latitude":"48.09806","longitude":"7.02361","population":"91","region":"44","departement":"88","arrondissement":"883","commune":"88492"}
]