[
{"name":"Villeneuve-de-Berg","latitude":"44.55694","longitude":"4.50222","population":"2835","region":"84","departement":"07","arrondissement":"071","commune":"07341"},
{"name":"Vallon-Pont-d'Arc","latitude":"44.40694","longitude":"4.39361","population":"2337","region":"84","departement":"07","arrondissement":"071","commune":"07330"},
{"name":"Ruoms","latitude":"44.45306","longitude":"4.34194","population":"2249","region":"84","departement":"07","arrondissement":"071","commune":"07201"},
{"name":"Lavilledieu","latitude":"44.57556","longitude":"4.45306","population":"1897","region":"84","departement":"07","arrondissement":"071","commune":"07138"},
{"name":"Largentière","latitude":"44.54278","longitude":"4.29333","population":"1814","region":"84","departement":"07","arrondissement":"071","commune":"07132"},
{"name":"Joyeuse","latitude":"44.47944","longitude":"4.23778","population":"1640","region":"84","departement":"07","arrondissement":"071","commune":"07110"},
{"name":"Saint-Sernin","latitude":"44.57139","longitude":"4.39194","population":"1522","region":"84","departement":"07","arrondissement":"071","commune":"07296"},
{"name":"Lachapelle-sous-Aubenas","latitude":"44.5644","longitude":"4.3649","population":"1450","region":"84","departement":"07","arrondissement":"071","commune":"07122"},
{"name":"Vinezac","latitude":"44.5383","longitude":"4.3262","population":"1214","region":"84","departement":"07","arrondissement":"071","commune":"07343"},
{"name":"Rosières","latitude":"44.48333","longitude":"4.2575","population":"1121","region":"84","departement":"07","arrondissement":"071","commune":"07199"},
{"name":"Chassiers","latitude":"44.55083","longitude":"4.29694","population":"1008","region":"84","departement":"07","arrondissement":"071","commune":"07058"},
{"name":"Saint-Alban-Auriolles","latitude":"44.4258","longitude":"4.2992","population":"994","region":"84","departement":"07","arrondissement":"071","commune":"07207"},
{"name":"Lagorce","latitude":"44.44778","longitude":"4.41722","population":"977","region":"84","departement":"07","arrondissement":"071","commune":"07126"},
{"name":"Vogüé","latitude":"44.55056","longitude":"4.41444","population":"917","region":"84","departement":"07","arrondissement":"071","commune":"07348"},
{"name":"Laurac-en-Vivarais","latitude":"44.50861","longitude":"4.29056","population":"885","region":"84","departement":"07","arrondissement":"071","commune":"07134"},
{"name":"Saint-Remèze","latitude":"44.3925","longitude":"4.50194","population":"863","region":"84","departement":"07","arrondissement":"072","commune":"07291"},
{"name":"Grospierres","latitude":"44.40056","longitude":"4.28917","population":"861","region":"84","departement":"07","arrondissement":"071","commune":"07101"},
{"name":"Saint-Germain","latitude":"44.5545","longitude":"4.4513","population":"627","region":"84","departement":"07","arrondissement":"071","commune":"07241"},
{"name":"Labeaume","latitude":"44.4492","longitude":"4.3073","population":"607","region":"84","departement":"07","arrondissement":"071","commune":"07115"},
{"name":"Gras","latitude":"44.4438","longitude":"4.5404","population":"537","region":"84","departement":"07","arrondissement":"072","commune":"07099"},
{"name":"Montréal","latitude":"44.5284","longitude":"4.2938","population":"535","region":"84","departement":"07","arrondissement":"071","commune":"07162"},
{"name":"Salavas","latitude":"44.39417","longitude":"4.37917","population":"530","region":"84","departement":"07","arrondissement":"071","commune":"07304"},
{"name":"Vagnas","latitude":"44.34583","longitude":"4.36694","population":"521","region":"84","departement":"07","arrondissement":"071","commune":"07328"},
{"name":"Chandolas","latitude":"44.40361","longitude":"4.25278","population":"456","region":"84","departement":"07","arrondissement":"071","commune":"07053"},
{"name":"Beaulieu","latitude":"44.361","longitude":"4.2344","population":"446","region":"84","departement":"07","arrondissement":"071","commune":"07028"},
{"name":"Uzer","latitude":"44.51917","longitude":"4.32639","population":"428","region":"84","departement":"07","arrondissement":"071","commune":"07327"},
{"name":"Pradons","latitude":"44.47444","longitude":"4.35889","population":"421","region":"84","departement":"07","arrondissement":"071","commune":"07183"},
{"name":"Sanilhac","latitude":"44.5356","longitude":"4.2506","population":"393","region":"84","departement":"07","arrondissement":"071","commune":"07307"},
{"name":"Lanas","latitude":"44.5311","longitude":"4.4","population":"384","region":"84","departement":"07","arrondissement":"071","commune":"07131"},
{"name":"Joannas","latitude":"44.56556","longitude":"4.25167","population":"342","region":"84","departement":"07","arrondissement":"071","commune":"07109"},
{"name":"Chauzon","latitude":"44.48528","longitude":"4.36028","population":"341","region":"84","departement":"07","arrondissement":"071","commune":"07061"},
{"name":"Balazuc","latitude":"44.50861","longitude":"4.3725","population":"336","region":"84","departement":"07","arrondissement":"071","commune":"07023"},
{"name":"Saint-Maurice-d'Ardèche","latitude":"44.52111","longitude":"4.39972","population":"312","region":"84","departement":"07","arrondissement":"071","commune":"07272"},
{"name":"Fons","latitude":"44.5833","longitude":"4.3496","population":"308","region":"84","departement":"07","arrondissement":"071","commune":"07091"},
{"name":"Rocher","latitude":"44.577","longitude":"4.2857","population":"277","region":"84","departement":"07","arrondissement":"071","commune":"07193"},
{"name":"Labastide-de-Virac","latitude":"44.35028","longitude":"4.40333","population":"225","region":"84","departement":"07","arrondissement":"071","commune":"07113"},
{"name":"Rochecolombe","latitude":"44.5176","longitude":"4.436","population":"225","region":"84","departement":"07","arrondissement":"071","commune":"07190"},
{"name":"Sampzon","latitude":"44.42472","longitude":"4.34333","population":"224","region":"84","departement":"07","arrondissement":"071","commune":"07306"},
{"name":"Vernon","latitude":"44.5075","longitude":"4.22528","population":"220","region":"84","departement":"07","arrondissement":"071","commune":"07336"},
{"name":"Bessas","latitude":"44.34472","longitude":"4.3025","population":"207","region":"84","departement":"07","arrondissement":"071","commune":"07033"},
{"name":"Saint-Maurice-d'Ibie","latitude":"44.50111","longitude":"4.48306","population":"206","region":"84","departement":"07","arrondissement":"071","commune":"07273"},
{"name":"Tauriers","latitude":"44.55167","longitude":"4.28083","population":"180","region":"84","departement":"07","arrondissement":"071","commune":"07318"},
{"name":"Bidon","latitude":"44.36583","longitude":"4.53528","population":"176","region":"84","departement":"07","arrondissement":"072","commune":"07034"},
{"name":"Saint-Andéol-de-Berg","latitude":"44.52694","longitude":"4.52722","population":"133","region":"84","departement":"07","arrondissement":"071","commune":"07208"}
]