[
{"name":"Chantonnay","latitude":"46.68694","longitude":"-1.05056","population":"8168","region":"52","departement":"85","arrondissement":"852","commune":"85051"},
{"name":"Pouzauges","latitude":"46.78222","longitude":"-0.83722","population":"5428","region":"52","departement":"85","arrondissement":"851","commune":"85182"},
{"name":"Le Boupère","latitude":"46.79472","longitude":"-0.92639","population":"2898","region":"52","departement":"85","arrondissement":"851","commune":"85031"},
{"name":"La Châtaigneraie","latitude":"46.64944","longitude":"-0.74028","population":"2641","region":"52","departement":"85","arrondissement":"851","commune":"85059"},
{"name":"Saint-Mesmin","latitude":"46.79333","longitude":"-0.73417","population":"1819","region":"52","departement":"85","arrondissement":"851","commune":"85254"},
{"name":"Montournais","latitude":"46.74167","longitude":"-0.76306","population":"1725","region":"52","departement":"85","arrondissement":"851","commune":"85147"},
{"name":"La Meilleraie-Tillay","latitude":"46.74111","longitude":"-0.84639","population":"1519","region":"52","departement":"85","arrondissement":"851","commune":"85140"},
{"name":"Saint-Germain-de-Prinçay","latitude":"46.72083","longitude":"-1.02167","population":"1482","region":"52","departement":"85","arrondissement":"852","commune":"85220"},
{"name":"Saint-Prouant","latitude":"46.75833","longitude":"-0.95694","population":"1472","region":"52","departement":"85","arrondissement":"852","commune":"85266"},
{"name":"La Tardière","latitude":"46.66056","longitude":"-0.73333","population":"1286","region":"52","departement":"85","arrondissement":"851","commune":"85289"},
{"name":"Mouilleron-Saint-Germain","latitude":"46.67583","longitude":"-0.84944","population":"1280","region":"52","departement":"85","arrondissement":"851","commune":"85154"},
{"name":"Bazoges-en-Pareds","latitude":"46.65611","longitude":"-0.91611","population":"1166","region":"52","departement":"85","arrondissement":"851","commune":"85014"},
{"name":"La Caillère-Saint-Hilaire","latitude":"46.6182","longitude":"-0.91","population":"1056","region":"52","departement":"85","arrondissement":"851","commune":"85040"},
{"name":"La Réorthe","latitude":"46.60694","longitude":"-1.04972","population":"1017","region":"52","departement":"85","arrondissement":"851","commune":"85188"},
{"name":"Antigny","latitude":"46.62","longitude":"-0.76944","population":"1015","region":"52","departement":"85","arrondissement":"851","commune":"85005"},
{"name":"Cheffois","latitude":"46.66861","longitude":"-0.79139","population":"946","region":"52","departement":"85","arrondissement":"851","commune":"85067"},
{"name":"Monsireigne","latitude":"46.7451","longitude":"-0.9469","population":"891","region":"52","departement":"85","arrondissement":"851","commune":"85145"},
{"name":"Vouvant","latitude":"46.57194","longitude":"-0.76917","population":"860","region":"52","departement":"85","arrondissement":"851","commune":"85305"},
{"name":"Rochetrejoux","latitude":"46.7892","longitude":"-0.9955","population":"844","region":"52","departement":"85","arrondissement":"852","commune":"85192"},
{"name":"Sigournais","latitude":"46.70667","longitude":"-0.98639","population":"826","region":"52","departement":"85","arrondissement":"852","commune":"85282"},
{"name":"Réaumur","latitude":"46.71944","longitude":"-0.80167","population":"807","region":"52","departement":"85","arrondissement":"851","commune":"85187"},
{"name":"Chavagnes-les-Redoux","latitude":"46.71667","longitude":"-0.91861","population":"793","region":"52","departement":"85","arrondissement":"851","commune":"85066"},
{"name":"Thouarsais-Bouildroux","latitude":"46.61917","longitude":"-0.88028","population":"703","region":"52","departement":"85","arrondissement":"851","commune":"85292"},
{"name":"Menomblet","latitude":"46.73167","longitude":"-0.71194","population":"653","region":"52","departement":"85","arrondissement":"851","commune":"85141"},
{"name":"Saint-Maurice-des-Noues","latitude":"46.6025","longitude":"-0.72306","population":"624","region":"52","departement":"85","arrondissement":"851","commune":"85251"},
{"name":"Saint-Maurice-le-Girard","latitude":"46.6434","longitude":"-0.8038","population":"595","region":"52","departement":"85","arrondissement":"851","commune":"85252"},
{"name":"La Jaudonnière","latitude":"46.6434","longitude":"-0.9622","population":"583","region":"52","departement":"85","arrondissement":"851","commune":"85115"},
{"name":"Saint-Cyr-des-Gâts","latitude":"46.56917","longitude":"-0.88444","population":"521","region":"52","departement":"85","arrondissement":"851","commune":"85205"},
{"name":"Tallud-Sainte-Gemme","latitude":"46.68667","longitude":"-0.88528","population":"460","region":"52","departement":"85","arrondissement":"851","commune":"85287"},
{"name":"Saint-Juire-Champgillon","latitude":"46.57806","longitude":"-1.02722","population":"430","region":"52","departement":"85","arrondissement":"851","commune":"85235"},
{"name":"Saint-Martin-Lars-en-Sainte-Hermine","latitude":"46.5912","longitude":"-0.9802","population":"414","region":"52","departement":"85","arrondissement":"851","commune":"85248"},
{"name":"Saint-Sulpice-en-Pareds","latitude":"46.60167","longitude":"-0.83556","population":"392","region":"52","departement":"85","arrondissement":"851","commune":"85271"},
{"name":"Saint-Laurent-de-la-Salle","latitude":"46.56889","longitude":"-0.91778","population":"371","region":"52","departement":"85","arrondissement":"851","commune":"85237"},
{"name":"Cezais","latitude":"46.5894","longitude":"-0.8182","population":"323","region":"52","departement":"85","arrondissement":"851","commune":"85041"}
]