[
{"name":"La Ferté-Macé","latitude":"48.5925","longitude":"-0.35722","population":"6013","region":"28","departement":"61","arrondissement":"611","commune":"61168"},
{"name":"Domfront en Poiraie","latitude":"48.59028","longitude":"-0.64028","population":"3866","region":"28","departement":"61","arrondissement":"611","commune":"61145"},
{"name":"Bagnoles de l'Orne Normandie","latitude":"48.555","longitude":"-0.41111","population":"2454","region":"28","departement":"61","arrondissement":"611","commune":"61483"},
{"name":"La Ferrière-aux-Étangs","latitude":"48.66227","longitude":"-0.51955","population":"1561","region":"28","departement":"61","arrondissement":"612","commune":"61163"},
{"name":"Rives d'Andaine","latitude":"48.53281","longitude":"-0.47872","population":"1542","region":"28","departement":"61","arrondissement":"611","commune":"61096"},
{"name":"Ceaucé","latitude":"48.49436","longitude":"-0.62526","population":"1219","region":"28","departement":"61","arrondissement":"611","commune":"61075"},
{"name":"Bellou-en-Houlme","latitude":"48.69083","longitude":"-0.44361","population":"1096","region":"28","departement":"61","arrondissement":"612","commune":"61040"},
{"name":"Juvigny Val d'Andaine","latitude":"48.55083","longitude":"-0.5075","population":"1065","region":"28","departement":"61","arrondissement":"611","commune":"61211"},
{"name":"Saint-Bômer-les-Forges","latitude":"48.6441","longitude":"-0.63293","population":"1040","region":"28","departement":"61","arrondissement":"611","commune":"61369"},
{"name":"Champsecret","latitude":"48.60925","longitude":"-0.55058","population":"1021","region":"28","departement":"61","arrondissement":"611","commune":"61091"},
{"name":"Les Monts d'Andaine","latitude":"48.62346","longitude":"-0.41632","population":"945","region":"28","departement":"61","arrondissement":"611","commune":"61463"},
{"name":"Saint-Clair-de-Halouze","latitude":"48.67917","longitude":"-0.62528","population":"860","region":"28","departement":"61","arrondissement":"611","commune":"61376"},
{"name":"Banvou","latitude":"48.66536","longitude":"-0.55238","population":"632","region":"28","departement":"61","arrondissement":"612","commune":"61024"},
{"name":"Saint-Fraimbault","latitude":"48.4866","longitude":"-0.6985","population":"617","region":"28","departement":"61","arrondissement":"611","commune":"61387"},
{"name":"Le Ménil-de-Briouze","latitude":"48.67626","longitude":"-0.39978","population":"538","region":"28","departement":"61","arrondissement":"612","commune":"61260"},
{"name":"La Coulonche","latitude":"48.64705","longitude":"-0.45653","population":"516","region":"28","departement":"61","arrondissement":"612","commune":"61124"},
{"name":"Perrou","latitude":"48.57306","longitude":"-0.55722","population":"397","region":"28","departement":"61","arrondissement":"611","commune":"61326"},
{"name":"Le Châtellier","latitude":"48.676","longitude":"-0.5815","population":"388","region":"28","departement":"61","arrondissement":"612","commune":"61102"},
{"name":"Tessé-Froulay","latitude":"48.52722","longitude":"-0.43184","population":"364","region":"28","departement":"61","arrondissement":"611","commune":"61482"},
{"name":"Madré","latitude":"48.47742","longitude":"-0.37971","population":"363","region":"52","departement":"53","arrondissement":"533","commune":"53142"},
{"name":"Dompierre","latitude":"48.6328","longitude":"-0.55228","population":"360","region":"28","departement":"61","arrondissement":"612","commune":"61146"},
{"name":"Thubœuf","latitude":"48.50222","longitude":"-0.45111","population":"296","region":"52","departement":"53","arrondissement":"533","commune":"53263"},
{"name":"Torchamp","latitude":"48.54667","longitude":"-0.69778","population":"289","region":"28","departement":"61","arrondissement":"611","commune":"61487"},
{"name":"Saires-la-Verrerie","latitude":"48.68779","longitude":"-0.49061","population":"280","region":"28","departement":"61","arrondissement":"612","commune":"61459"},
{"name":"Saint-Julien-du-Terroux","latitude":"48.47925","longitude":"-0.4095","population":"268","region":"52","departement":"53","arrondissement":"533","commune":"53230"},
{"name":"Lonlay-le-Tesson","latitude":"48.64347","longitude":"-0.35347","population":"246","region":"28","departement":"61","arrondissement":"611","commune":"61233"},
{"name":"Sainte-Marie-du-Bois","latitude":"48.4652","longitude":"-0.48166","population":"236","region":"52","departement":"53","arrondissement":"533","commune":"53235"},
{"name":"Le Housseau-Brétignolles","latitude":"48.4686","longitude":"-0.5212","population":"231","region":"52","departement":"53","arrondissement":"533","commune":"53118"},
{"name":"Soucé","latitude":"48.47444","longitude":"-0.66444","population":"195","region":"52","departement":"53","arrondissement":"533","commune":"53261"},
{"name":"Saint-Brice","latitude":"48.5586","longitude":"-0.6424","population":"163","region":"28","departement":"61","arrondissement":"611","commune":"61370"},
{"name":"Avrilly","latitude":"48.53948","longitude":"-0.61481","population":"125","region":"28","departement":"61","arrondissement":"611","commune":"61021"},
{"name":"Antoigny","latitude":"48.52436","longitude":"-0.36495","population":"116","region":"28","departement":"61","arrondissement":"611","commune":"61004"},
{"name":"Rennes-en-Grenouilles","latitude":"48.4929","longitude":"-0.51288","population":"111","region":"52","departement":"53","arrondissement":"533","commune":"53189"},
{"name":"Méhoudin","latitude":"48.50171","longitude":"-0.38499","population":"109","region":"28","departement":"61","arrondissement":"611","commune":"61257"},
{"name":"Saint-Gilles-des-Marais","latitude":"48.58287","longitude":"-0.69388","population":"99","region":"28","departement":"61","arrondissement":"611","commune":"61401"}
]