[
{"name":"Sainte-Sigolène","latitude":"45.24306","longitude":"4.23472","population":"5900","region":"84","departement":"43","arrondissement":"433","commune":"43224"},
{"name":"Saint-Didier-en-Velay","latitude":"45.30278","longitude":"4.27528","population":"3313","region":"84","departement":"43","arrondissement":"433","commune":"43177"},
{"name":"Tence","latitude":"45.11417","longitude":"4.29111","population":"3232","region":"84","departement":"43","arrondissement":"433","commune":"43244"},
{"name":"Bourg-Argental","latitude":"45.29639","longitude":"4.56","population":"3008","region":"84","departement":"42","arrondissement":"423","commune":"42023"},
{"name":"Dunières","latitude":"45.21556","longitude":"4.34472","population":"2939","region":"84","departement":"43","arrondissement":"433","commune":"43087"},
{"name":"Saint-Pal-de-Mons","latitude":"45.2466","longitude":"4.2749","population":"2060","region":"84","departement":"43","arrondissement":"433","commune":"43213"},
{"name":"Marlhes","latitude":"45.28306","longitude":"4.39472","population":"1388","region":"84","departement":"42","arrondissement":"423","commune":"42139"},
{"name":"La Séauve-sur-Semène","latitude":"45.2952","longitude":"4.2506","population":"1363","region":"84","departement":"43","arrondissement":"433","commune":"43236"},
{"name":"Montfaucon-en-Velay","latitude":"45.1854","longitude":"4.3145","population":"1270","region":"84","departement":"43","arrondissement":"433","commune":"43141"},
{"name":"Jonzieux","latitude":"45.31361","longitude":"4.36222","population":"1232","region":"84","departement":"42","arrondissement":"423","commune":"42115"},
{"name":"Riotord","latitude":"45.23167","longitude":"4.40194","population":"1189","region":"84","departement":"43","arrondissement":"433","commune":"43163"},
{"name":"Saint-Sauveur-en-Rue","latitude":"45.26944","longitude":"4.495","population":"1118","region":"84","departement":"42","arrondissement":"423","commune":"42287"},
{"name":"Saint-Romain-Lachalm","latitude":"45.26667","longitude":"4.33333","population":"1049","region":"84","departement":"43","arrondissement":"433","commune":"43223"},
{"name":"Vanosc","latitude":"45.22444","longitude":"4.55056","population":"885","region":"84","departement":"07","arrondissement":"073","commune":"07333"},
{"name":"Raucoules","latitude":"45.1875","longitude":"4.295","population":"874","region":"84","departement":"43","arrondissement":"433","commune":"43159"},
{"name":"Saint-Victor-Malescours","latitude":"45.29167","longitude":"4.31222","population":"758","region":"84","departement":"43","arrondissement":"433","commune":"43227"},
{"name":"Montregard","latitude":"45.15861","longitude":"4.34667","population":"609","region":"84","departement":"43","arrondissement":"433","commune":"43142"},
{"name":"Vocance","latitude":"45.20139","longitude":"4.5525","population":"608","region":"84","departement":"07","arrondissement":"073","commune":"07347"},
{"name":"Lalouvesc","latitude":"45.12028","longitude":"4.535","population":"496","region":"84","departement":"07","arrondissement":"073","commune":"07128"},
{"name":"Saint-Régis-du-Coin","latitude":"45.28389","longitude":"4.44417","population":"375","region":"84","departement":"42","arrondissement":"423","commune":"42280"},
{"name":"La Versanne","latitude":"45.3175","longitude":"4.52583","population":"359","region":"84","departement":"42","arrondissement":"423","commune":"42329"},
{"name":"Burdignes","latitude":"45.27028","longitude":"4.56667","population":"348","region":"84","departement":"42","arrondissement":"423","commune":"42028"},
{"name":"Chenereilles","latitude":"45.13333","longitude":"4.25194","population":"291","region":"84","departement":"43","arrondissement":"433","commune":"43069"},
{"name":"Saint-Julien-Vocance","latitude":"45.17528","longitude":"4.50306","population":"252","region":"84","departement":"07","arrondissement":"073","commune":"07258"},
{"name":"Saint-André-en-Vivarais","latitude":"45.12111","longitude":"4.41111","population":"228","region":"84","departement":"07","arrondissement":"073","commune":"07212"},
{"name":"Saint-Bonnet-le-Froid","latitude":"45.14324","longitude":"4.43521","population":"228","region":"84","departement":"43","arrondissement":"433","commune":"43172"},
{"name":"Saint-Julien-Molhesabate","latitude":"45.18611","longitude":"4.42639","population":"208","region":"84","departement":"43","arrondissement":"433","commune":"43204"},
{"name":"Thélis-la-Combe","latitude":"45.3276","longitude":"4.5557","population":"175","region":"84","departement":"42","arrondissement":"423","commune":"42310"},
{"name":"Le Mas-de-Tence","latitude":"45.12139","longitude":"4.35944","population":"170","region":"84","departement":"43","arrondissement":"433","commune":"43129"},
{"name":"Saint-Symphorien-de-Mahun","latitude":"45.16417","longitude":"4.56","population":"130","region":"84","departement":"07","arrondissement":"073","commune":"07299"},
{"name":"Saint-Pierre-sur-Doux","latitude":"45.1206","longitude":"4.4648","population":"103","region":"84","departement":"07","arrondissement":"073","commune":"07285"},
{"name":"Monestier","latitude":"45.19861","longitude":"4.53111","population":"53","region":"84","departement":"07","arrondissement":"073","commune":"07160"}
]