[
{"name":"Gien","latitude":"47.6892","longitude":"2.6297","population":"15161","region":"24","departement":"45","arrondissement":"451","commune":"45155"},
{"name":"Amilly","latitude":"47.9736","longitude":"2.771","population":"11621","region":"24","departement":"45","arrondissement":"451","commune":"45004"},
{"name":"Châteauneuf-sur-Loire","latitude":"47.86528","longitude":"2.22222","population":"7927","region":"24","departement":"45","arrondissement":"452","commune":"45082"},
{"name":"Briare","latitude":"47.63806","longitude":"2.73917","population":"5688","region":"24","departement":"45","arrondissement":"451","commune":"45053"},
{"name":"Sully-sur-Loire","latitude":"47.765","longitude":"2.37528","population":"5556","region":"24","departement":"45","arrondissement":"452","commune":"45315"}
]