[
{"name":"Le Mans","latitude":"48.00417","longitude":"0.19694","population":"142281","region":"52","departement":"72","arrondissement":"723","commune":"72181"},
{"name":"Alençon","latitude":"48.42972","longitude":"0.09194","population":"27325","region":"28","departement":"61","arrondissement":"611","commune":"61001"},
{"name":"La Ferté-Bernard","latitude":"48.18667","longitude":"0.65444","population":"9278","region":"52","departement":"72","arrondissement":"722","commune":"72132"},
{"name":"Coulaines","latitude":"48.0267","longitude":"0.2051","population":"7441","region":"52","departement":"72","arrondissement":"723","commune":"72095"},
{"name":"Mamers","latitude":"48.34944","longitude":"0.36944","population":"5545","region":"52","departement":"72","arrondissement":"722","commune":"72180"}
]